fex.cp313-win_amd64.pyd
fex_crypto-1.0b1.dist-info/METADATA
fex_crypto-1.0b1.dist-info/WHEEL
fex_crypto-1.0b1.dist-info/top_level.txt
fex_crypto-1.0b1.dist-info/RECORD
