Metadata-Version: 2.4
Name: fex-crypto
Version: 1.0b1
Summary: FEX v1.0-beta: Fast Encryption eXchange (novel symmetric cipher)
Home-page: https://github.com/BronioInt/fex
Author: Bronio Int
Author-email: bronio.int@example.com
Classifier: Programming Language :: Python :: 3
Classifier: Programming Language :: C++
Classifier: License :: OSI Approved :: MIT License
Classifier: Operating System :: OS Independent
Classifier: Development Status :: 3 - Alpha
Classifier: Intended Audience :: Developers
Classifier: Topic :: Security :: Cryptography
Requires-Python: >=3.6
Dynamic: author
Dynamic: author-email
Dynamic: classifier
Dynamic: description
Dynamic: description-content-type
Dynamic: home-page
Dynamic: requires-python
Dynamic: summary
